imageboard/__init__.py
imageboard/py.typed
imageboard/fonts/Roboto-Bold.ttf
imageboard-0.3.1.dist-info/METADATA
imageboard-0.3.1.dist-info/WHEEL
imageboard-0.3.1.dist-info/RECORD
