Metadata-Version: 2.4
Name: imageboard
Version: 0.3.1
Summary: imageboard is a simple image display tool. Aim to provide a simple way to share experimental results.
Author-email: Jianqi Pan <jannchie@gmail.com>
Requires-Python: >=3.10
Requires-Dist: matplotlib>=3.9.3
Requires-Dist: pillow>=11.0.0
Requires-Dist: pydantic>=2.10.3
